setup.py
activity_logger/__init__.py
activity_logger/admin.py
activity_logger/forms.py
activity_logger/models.py
activity_logger/tests.py
activity_logger/urls.py
activity_logger/utils.py
activity_logger/views.py
activity_logger/middleware/__init__.py
activity_logger/middleware/activity_logger.py
activity_logger/migrations/0001_initial.py
activity_logger/migrations/__init__.py
activity_logger/templatetags/__init__.py
activity_logger/templatetags/activity_logger.py
django_activity_logger.egg-info/PKG-INFO
django_activity_logger.egg-info/SOURCES.txt
django_activity_logger.egg-info/dependency_links.txt
django_activity_logger.egg-info/not-zip-safe
django_activity_logger.egg-info/requires.txt
django_activity_logger.egg-info/top_level.txt